syllabub-0.1.6.dist-info/METADATA
syllabub-0.1.6.dist-info/WHEEL
syllabub-0.1.6.dist-info/entry_points.txt
syllabub-0.1.6.dist-info/licenses/COPYING
syllabub-0.1.6.dist-info/licenses/LICENSES/AGPL-3.0-or-later.txt
syllabub-0.1.6.dist-info/licenses/LICENSES/CC-BY-4.0.txt
syllabub-0.1.6.dist-info/licenses/LICENSES/CC-BY-SA-3.0.txt
syllabub-0.1.6.dist-info/licenses/LICENSES/CC-BY-SA-4.0.txt
syllabub-0.1.6.dist-info/licenses/LICENSES/CC0-1.0.txt
syllabub-0.1.6.dist-info/licenses/LICENSES/LicenseRef-DCO-1.1-license.txt
syllabub/__init__.py
syllabub/builtin/.gitignore.mustache
syllabub/builtin/.gitignore.mustache.license
syllabub/builtin/CONDUCT.COVENANT
syllabub/builtin/CONDUCT.COVENANT.license
syllabub/builtin/CONDUCT.UBUNTU
syllabub/builtin/CONDUCT.UBUNTU.license
syllabub/builtin/CONTRIBUTING.DCO
syllabub/builtin/CONTRIBUTING.DCO.LICENSEREF
syllabub/builtin/CONTRIBUTING.DCO.LICENSEREF.license
syllabub/builtin/CONTRIBUTING.DCO.license
syllabub/builtin/LicenseRef-DCO-1.1-license.txt
syllabub/builtin/LicenseRef-DCO-1.1-license.txt.license
syllabub/builtin/Makefile.mustache
syllabub/builtin/Makefile.mustache.license
syllabub/builtin/README.md.mustache
syllabub/builtin/README.md.mustache.license
syllabub/builtin/__init__.py
syllabub/builtin/cli.py.mustache
syllabub/builtin/cli.py.mustache.license
syllabub/builtin/logo.png
syllabub/builtin/logo.png.license
syllabub/builtin/pdm.lock.license.mustache
syllabub/builtin/pdm.lock.license.mustache.license
syllabub/builtin/pyproject.toml.mustache
syllabub/builtin/pyproject.toml.mustache.license
syllabub/builtin/test_cli.py.mustache
syllabub/builtin/test_cli.py.mustache.license
syllabub/cli.py
syllabub/metadata.py
syllabub-0.1.6.dist-info/RECORD
