Metadata-Version: 2.1
Name: syllabub
Version: 0.1.6
Summary: Keep Python project conventions up-to-date and worry less about trifling matters. 🍰
Author-Email: David Seaward <david@librem.one>
License: AGPL-3.0-or-later
Project-URL: Source, https://gitlab.com/lfdo/toolchain/syllabub
Project-URL: Project, https://lofidevops.neocities.org
Requires-Python: >=3.10
Requires-Dist: chevron>=0.14.0
Requires-Dist: tomli>=2.0.1
